setup_django_apex/__init__.py
setup_django_apex/installer.py
tests/__init__.py
tests/mytest.py
tests/test_installer.py
setup_django_apex-0.1.10.dist-info/LICENSE
setup_django_apex-0.1.10.dist-info/METADATA
setup_django_apex-0.1.10.dist-info/WHEEL
setup_django_apex-0.1.10.dist-info/entry_points.txt
setup_django_apex-0.1.10.dist-info/top_level.txt
setup_django_apex-0.1.10.dist-info/RECORD
