Metadata-Version: 2.1
Name: setup_django_apex
Version: 0.1.10
Summary: A library to set up Django projects with multiple apps
Home-page: https://github.com/Anirudha1821/setup_django_apex
Author: Anirudha Udgirkar
Author-email: anirudhaudgirkar.work.email@example.com
License: MIT License
Classifier: Programming Language :: Python :: 3
Classifier: License :: OSI Approved :: MIT License
Classifier: Operating System :: OS Independent
Requires-Python: >=3.6
License-File: LICENSE
Requires-Dist: Django >=3.0
